{
    "bookInfo": [{
        "title" : "physics",
        "rating" : 7.5,
        "description" : "amazing book",
        "author" : "rajesh agarwal",
        "id" : 1
    },
    {
  "title": "maths",
  "rating": 7.5,
  "description": "amazing book",
  "author": "rajesh agarwal",
  "id": 2
}, {
  "title": "maths",
  "rating": 7.5,
  "description": "amazing book",
  "author": "rajesh agarwal",
  "id": 3
}, {
  "title": "maths",
  "rating": 7.5,
  "description": "amazing book",
  "author": "rajesh agarwal",
  "id": 4
}, {
  "title": "maths",
  "rating": 7.5,
  "description": "amazing book",
  "author": "rajesh agarwal",
  "id": 5
}, {
  "title": "maths",
  "rating": 7.5,
  "description": "amazing book",
  "author": "rajesh agarwal",
  "id": 6
}, {
  "title": "maths",
  "rating": 7.5,
  "description": "amazing book",
  "author": "rajesh agarwal",
  "id": 7
}, {
  "title": "maths",
  "rating": 7.5,
  "description": "amazing book",
  "author": "rajesh agarwal",
  "id": 8
}, {
  "title": "maths",
  "rating": 7.5,
  "description": "amazing book",
  "author": "rajesh agarwal",
  "id": 9
}, {
  "title": "maths",
  "rating": 7.5,
  "description": "amazing book",
  "author": "rajesh agarwal",
  "id": 10
}, {
  "title": "maths",
  "rating": 7.5,
  "description": "amazing book",
  "author": "rajesh agarwal",
  "id": 11
}, {
  "title": "maths",
  "rating": 7.5,
  "description": "amazing book",
  "author": "rajesh agarwal",
  "id": 12
}, {
  "title": "maths",
  "rating": 7.5,
  "description": "amazing book",
  "author": "rajesh agarwal",
  "id": 13
}, {
  "title": "maths",
  "rating": 7.5,
  "description": "amazing book",
  "author": "rajesh agarwal",
  "id": 14
}, {
  "title": "maths",
  "rating": 7.5,
  "description": "amazing book",
  "author": "rajesh agarwal",
  "id": 15
}]
}